intelligenes/__init__.py
intelligenes/classification.py
intelligenes/intelligenes.py
intelligenes/selection.py
intelligenes-1.0.dist-info/LICENSE
intelligenes-1.0.dist-info/METADATA
intelligenes-1.0.dist-info/WHEEL
intelligenes-1.0.dist-info/entry_points.txt
intelligenes-1.0.dist-info/top_level.txt
intelligenes-1.0.dist-info/RECORD
